mlearn/__init__.py
mlearn/dhmm/DynamicHMM.py
mlearn/dhmm/EMAGMMHMM.py
mlearn/dhmm/EWMA.py
mlearn/dhmm/GMMHMM.py
mlearn/dhmm/_BaseHMM.py
mlearn/dhmm/_ContinuousHMM.py
mlearn/dhmm/__init__.py
mlearn/dhmm/weights.py
mlearn-0.0.3.dist-info/DESCRIPTION.rst
mlearn-0.0.3.dist-info/METADATA
mlearn-0.0.3.dist-info/RECORD
mlearn-0.0.3.dist-info/WHEEL
mlearn-0.0.3.dist-info/metadata.json
mlearn-0.0.3.dist-info/top_level.txt
