Metadata-Version: 2.0
Name: mlearn
Version: 0.0.3
Summary: Sequence machine learning algorithms
Home-page: https://github.com/X0Leon/mlearn
Author: Leon Zhang
Author-email: pku09zl@gmail.com
License: MIT
Keywords: python machine learning
Platform: UNKNOWN
Classifier: Development Status :: 3 - Alpha
Classifier: Topic :: Software Development :: Libraries
Classifier: Intended Audience :: Developers
Classifier: License :: OSI Approved :: MIT License
Classifier: Topic :: Software Development :: Libraries :: Python Modules
Classifier: Operating System :: OS Independent
Classifier: Programming Language :: Python
Classifier: Programming Language :: Python :: 3.5
Requires-Dist: numpy
Requires-Dist: scikit-learn
Requires-Dist: scipy
